python_cdo_wrapper/__init__.py
python_cdo_wrapper/cdo.py
python_cdo_wrapper/core.py
python_cdo_wrapper/exceptions.py
python_cdo_wrapper/parsers_legacy.py
python_cdo_wrapper/py.typed
python_cdo_wrapper/query.py
python_cdo_wrapper/shapefile_utils.py
python_cdo_wrapper/types_legacy.py
python_cdo_wrapper/utils.py
python_cdo_wrapper/validation.py
python_cdo_wrapper/operators/__init__.py
python_cdo_wrapper/operators/base.py
python_cdo_wrapper/operators/info.py
python_cdo_wrapper/parsers/__init__.py
python_cdo_wrapper/parsers/base.py
python_cdo_wrapper/parsers/grid.py
python_cdo_wrapper/parsers/info.py
python_cdo_wrapper/types/__init__.py
python_cdo_wrapper/types/grid.py
python_cdo_wrapper/types/results.py
python_cdo_wrapper/types/variable.py
python_cdo_wrapper-1.1.2.dist-info/METADATA
python_cdo_wrapper-1.1.2.dist-info/WHEEL
python_cdo_wrapper-1.1.2.dist-info/licenses/LICENSE
python_cdo_wrapper-1.1.2.dist-info/RECORD
