Metadata-Version: 2.4
Name: python-cdo-wrapper
Version: 1.1.2
Summary: A simple, universal Python wrapper for CDO (Climate Data Operators) with seamless xarray integration
Project-URL: Bug Tracker, https://github.com/NarenKarthikBM/python-cdo-wrapper/issues
Project-URL: Changelog, https://github.com/NarenKarthikBM/python-cdo-wrapper/blob/main/CHANGELOG.md
Project-URL: Documentation, https://github.com/NarenKarthikBM/python-cdo-wrapper#readme
Project-URL: Homepage, https://github.com/NarenKarthikBM/python-cdo-wrapper
Project-URL: Repository, https://github.com/NarenKarthikBM/python-cdo-wrapper
Author-email: B M Naren Karthik <narenkarthikbm@gmail.com>
Maintainer-email: B M Naren Karthik <narenkarthikbm@gmail.com>
License-Expression: MIT
License-File: LICENSE
Keywords: cdo,climate,climate-data,climate-science,earth-science,grib,jupyter,meteorology,netcdf,weather,xarray
Classifier: Development Status :: 4 - Beta
Classifier: Environment :: Console
Classifier: Intended Audience :: Developers
Classifier: Intended Audience :: Science/Research
Classifier: License :: OSI Approved :: MIT License
Classifier: Operating System :: MacOS
Classifier: Operating System :: POSIX :: Linux
Classifier: Operating System :: Unix
Classifier: Programming Language :: Python :: 3
Classifier: Programming Language :: Python :: 3.9
Classifier: Programming Language :: Python :: 3.10
Classifier: Programming Language :: Python :: 3.11
Classifier: Programming Language :: Python :: 3.12
Classifier: Programming Language :: Python :: 3.13
Classifier: Topic :: Scientific/Engineering
Classifier: Topic :: Scientific/Engineering :: Atmospheric Science
Classifier: Topic :: Scientific/Engineering :: GIS
Classifier: Topic :: Scientific/Engineering :: Hydrology
Classifier: Typing :: Typed
Requires-Python: >=3.9
Requires-Dist: netcdf4>=1.6.0
Requires-Dist: numpy>=1.22.0
Requires-Dist: typing-extensions>=4.0.0; python_version < '3.12'
Requires-Dist: xarray>=2023.1.0
Provides-Extra: dev
Requires-Dist: build>=1.0.0; extra == 'dev'
Requires-Dist: hatch>=1.9.0; extra == 'dev'
Requires-Dist: mypy>=1.0.0; extra == 'dev'
Requires-Dist: pre-commit>=3.0.0; extra == 'dev'
Requires-Dist: pytest-cov>=4.0.0; extra == 'dev'
Requires-Dist: pytest>=7.0.0; extra == 'dev'
Requires-Dist: ruff>=0.1.0; extra == 'dev'
Requires-Dist: twine>=4.0.0; extra == 'dev'
Provides-Extra: docs
Requires-Dist: mkdocs-material>=9.0.0; extra == 'docs'
Requires-Dist: mkdocs>=1.5.0; extra == 'docs'
Requires-Dist: mkdocstrings[python]>=0.24.0; extra == 'docs'
Provides-Extra: shapefiles
Requires-Dist: geopandas>=0.10.0; extra == 'shapefiles'
Requires-Dist: shapely>=2.0.0; extra == 'shapefiles'
Provides-Extra: test
Requires-Dist: netcdf4>=1.6.0; extra == 'test'
Requires-Dist: pytest-cov>=4.0.0; extra == 'test'
Requires-Dist: pytest>=7.0.0; extra == 'test'
